{
  "appName": "PrinterHub",

  "tagline": "Java-based control and monitoring for USB-connected 3D printers",

  "subline": "Serial communication • G-code control • printer state modeling",

  "featureTitle": "Industrial-style device communication",

  "featureLeft1": "• USB serial interface handling",
  "featureLeft2": "• reliable G-code exchange",

  "featureRight1": "• printer state tracking",
  "featureRight2": "• future REST control layer",

  "chip1": "Java",
  "chip2": "Serial IO",
  "chip3": "G-code",
  "chip4": "REST API",

  "iconFile": "printerhub-icon.svg",

  "screenshot1": "printerhub-screenshot-1.png",
  "screenshot2": "printerhub-screenshot-2.png",

  "screenshot1Label": "Printer response logging",
  "screenshot2Label": "Serial communication test console",

  "shot1X": 900,
  "shot1Y": 62,
  "shot1Width": 300,
  "shot1Height": 300,
  "shot1Radius": 18,
  "shot1Fit": "xMidYMid meet",

  "shot2X": 1100,
  "shot2Y": 150,
  "shot2Width": 400,
  "shot2Height": 190,
  "shot2Radius": 18,
  "shot2Fit": "xMidYMid meet"
}